Workbook

Sheet LBO
C2: Leveraged Buyout of EA by Silver Lake, PIF, and Affinity Partners
C3: In Millions, expect per share data
B5: x | C5: GENERAL INPUTS & ASSUMPTIONS | F5: SOURCES & USES
C7: Company Name | D7: Electronic Arts | F7: Sources of Funds | G7: EBITDA Turns | J7: Uses of Funds
C8: Ticker | D8: NASDAQ: EA | F8: Excess Cash | G8: =H8/D12 -> 0.79533981 | H8: =D14-D15 -> 2048 | J8: Buyout of equity | L8: =D31 -> 54198.419
C9: Target share price | D9: 168.32 | F9: Revolver | G9: 0 | H9: =G9*D12 -> 0 | J9: Refinancing of debt | L9: =-D13 -> 1884
C10: Share price closing date | D10: 45925 | F10: Term loan | G10: 7 | H10: =G10*D12 -> 18025 | J10: Transaction and financing fees | L10: =J26+J29 -> 541.3671
F11: Senior note | G11: 0 | H11: =G11*D12 -> 0 | J11: Total Uses | L11: =SUM(L8:L10) -> 56623.786
C12: LTM EBITDA | D12: =Financials!F38 -> 2575 | F12: Sub note | G12: 0 | H12: =G12*D12 -> 0
C13: Gross Debt | D13: =-Financials!F67 -> -1884 | F13: Preferred stock | G13: 0 | H13: =G13*D12 -> 0
C14: Cash | D14: =Financials!F55 -> 2248 | F14: PIF rollover | G14: 2.03 | H14: =G14*D12 -> 5227.25
C15: Minimum cash | D15: 200 | F15: Sponsor equity | G15: =H15/D12 -> 12.16448 | H15: =L11-SUM(H8:H14) -> 31323.536
C16: EV/LTM EBITDA | D16: 31.5 | F16: Total Sources | H16: =SUM(H8:H15) -> 56623.786
C19: ENTRY VALUATION | H19: FEES
I20: % fees | J20: Fee | K20: Term | L20: Amortization
C21: Valuation Approach: | D21: 2 | E21: 1 | F21: 2 | H21: Financing Fees
D22: =CHOOSE($D$21,E22,F22) -> Offer/share | E22: EBITDA Multiple | F22: Offer/share | H22: Revolver | I22: 0.01 | J22: =I22*H9 -> 0 | K22: 5 | L22: =IFERROR(J22/K22,"NM") -> 0
H23: Term loan | I23: 0.015 | J23: =I23*H10 -> 270.375 | K23: 7 | L23: =IFERROR(J23/K23,"NM") -> 38.625
C24: LTM EBITDA | D24: =D12 -> 2575 | E24: =D12 -> 2575 | F24: =D12 -> 2575 | H24: Senior note | I24: 0.015 | J24: =I24*H11 -> 0 | L24: =IFERROR(J24/K24,"NM") -> NM
C25: EV/LTM EBITDA | D25: =CHOOSE($D$21,E25,F25) -> 20.906571 | E25: 22 | F25: =F26/F24 -> 20.906571 | H25: Sub note | I25: 0 | J25: =I25*H12 -> 0 | L25: =IFERROR(J25/K25,"NM") -> NM
C26: Enterprise Value | D26: =D24*D25 -> 53834.419 | E26: =E24*E25 -> 56650 | F26: =F31-SUM(F28:F29) -> 53834.419 | H26: Financing fees | J26: =SUM(J22:J25) -> 270.375 | L26: =SUM(L22:L23) -> 38.625
C28: Less: Gross debt | D28: =$D$13 -> -1884 | E28: =$D$13 -> -1884 | F28: =$D$13 -> -1884 | I28: % of Offer Value | J28: Fee
C29: Plus: Cash | D29: =$D$14 -> 2248 | E29: =$D$14 -> 2248 | F29: =$D$14 -> 2248 | H29: Transaction fees | I29: 0.005 | J29: =I29*D31 -> 270.9921
C31: Offer Value | D31: =D26+SUM(D28:D29) -> 54198.419 | E31: =E26+SUM(E28:E29) -> 57014 | F31: =F34*F32 -> 54198.419
C32: Diluted shares | D32: =DCF!$I$72 -> 258.08771 | E32: =DCF!$I$72 -> 258.08771 | F32: =DCF!$I$72 -> 258.08771
C34: Offer Value per share | D34: =D31/D32 -> 210 | E34: =E31/E32 -> 220.90939 | F34: 210
C35: Offer premium/discount | D35: =D34/$D$9-1 -> 0.24762357 | E35: =E34/$D$9-1 -> 0.31243699 | F35: =F34/$D$9-1 -> 0.24762357
B38: x | C38: EXIT VALUATION
G39: Step | H39: Assumed exit at March 31, 2030
C40: Exit EBITDA Multiple | G40: 5 | H40: =D16-10 -> 21.5 | I40: =H40+$G$40 -> 26.5 | J40: =I40+$G$40 -> 31.5 | K40: =J40+$G$40 -> 36.5 | L40: =K40+$G$40 -> 41.5
C41: Exit EBITDA | H41: =Financials!$K$38 -> 3506.0166 | I41: =Financials!$K$38 -> 3506.0166 | J41: =Financials!$K$38 -> 3506.0166 | K41: =Financials!$K$38 -> 3506.0166 | L41: =Financials!$K$38 -> 3506.0166
C42: Enterprise value | H42: =H41*H40 -> 75379.358 | I42: =I41*I40 -> 92909.441 | J42: =J41*J40 -> 110439.52 | K42: =K41*K40 -> 127969.61 | L42: =L41*L40 -> 145499.69
C44: Net Debt
C45: Revolver | H45: =Financials!$K$212 -> 0 | I45: =Financials!$K$212 -> 0 | J45: =Financials!$K$212 -> 0 | K45: =Financials!$K$212 -> 0 | L45: =Financials!$K$212 -> 0
C46: Term Loan | H46: =Financials!$K$218 -> 10206.373 | I46: =Financials!$K$218 -> 10206.373 | J46: =Financials!$K$218 -> 10206.373 | K46: =Financials!$K$218 -> 10206.373 | L46: =Financials!$K$218 -> 10206.373
C47: Senior Note | H47: =Financials!$K$225 -> 0 | I47: =Financials!$K$225 -> 0 | J47: =Financials!$K$225 -> 0 | K47: =Financials!$K$225 -> 0 | L47: =Financials!$K$225 -> 0
C48: Sub Note | H48: =Financials!$K$232 -> 0 | I48: =Financials!$K$232 -> 0 | J48: =Financials!$K$232 -> 0 | K48: =Financials!$K$232 -> 0 | L48: =Financials!$K$232 -> 0
C49: Pref. stock | H49: =Financials!$K$238 -> 0 | I49: =Financials!$K$238 -> 0 | J49: =Financials!$K$238 -> 0 | K49: =Financials!$K$238 -> 0 | L49: =Financials!$K$238 -> 0
C50: Cash | H50: =-Financials!$K$199 -> -200 | I50: =-Financials!$K$199 -> -200 | J50: =-Financials!$K$199 -> -200 | K50: =-Financials!$K$199 -> -200 | L50: =-Financials!$K$199 -> -200
C52: Equity value | E52: Initial Investment | F52: % Ownership | G52: Fully Diluted | H52: =H42-SUM(H45:H50) -> 65372.985 | I52: =I42-SUM(I45:I50) -> 82903.068 | J52: =J42-SUM(J45:J50) -> 100433.15 | K52: =K42-SUM(K45:K50) -> 117963.23 | L52: =L42-SUM(L45:L50) -> 135493.32
C53: Sponsor equity | E53: =H15 -> 31323.536 | F53: =E53/SUM($E$53:$E$56) -> 0.85698666 | G53: =(1-$G$55-$G$56)*(F53/SUM($F$53:$F$54)) -> 0.85698666 | H53: =H$52*$G53 -> 56023.776 | I53: =I$52*$G53 -> 71046.823 | J53: =J$52*$G53 -> 86069.871 | K53: =K$52*$G53 -> 101092.92 | L53: =L$52*$G53 -> 116115.97
C54: PIF rollover | E54: =H14 -> 5227.25 | F54: =E54/SUM($E$53:$E$56) -> 0.14301334 | G54: =(1-$G$55-$G$56)*(F54/SUM($F$53:$F$54)) -> 0.14301334 | H54: =H$52*$G54 -> 9349.2088 | I54: =I$52*$G54 -> 11856.245 | J54: =J$52*$G54 -> 14363.28 | K54: =K$52*$G54 -> 16870.316 | L54: =L$52*$G54 -> 19377.352
C55: Preferred stock | E55: =H13 -> 0 | F55: =E55/SUM($E$53:$E$56) -> 0 | H55: =H$52*$G55 -> 0 | I55: =I$52*$G55 -> 0 | J55: =J$52*$G55 -> 0 | K55: =K$52*$G55 -> 0 | L55: =L$52*$G55 -> 0
C56: Sub note | E56: =H12 -> 0 | F56: =E56/SUM($E$53:$E$56) -> 0 | H56: =H$52*$G56 -> 0 | I56: =I$52*$G56 -> 0 | J56: =J$52*$G56 -> 0 | K56: =K$52*$G56 -> 0 | L56: =L$52*$G56 -> 0
B59: x | C59: RETURNS
E60: Cash-on-cash | F60: IRR | G60: Initial | H60: 2026 | I60: =H60+1 -> 2027 | J60: =I60+1 -> 2028 | K60: =J60+1 -> 2029 | L60: =K60+1 -> 2030
C61: Revolver | E61: =IFERROR(SUM(H61:L61)/-G61,"NM") -> NM | F61: =IFERROR(IRR(G61:L61),0) -> 0 | G61: =-H9 -> 0 | H61: =-Financials!G211+Financials!G253 -> 0 | I61: =-Financials!H211+Financials!H253 -> 0 | J61: =-Financials!I211+Financials!I253 -> 0 | K61: =-Financials!J211+Financials!J253 -> 0 | L61: =-Financials!K211+Financials!K253+H45 -> 0
C62: Term Loan | E62: =IFERROR(SUM(H62:L62)/-G62,"NM") -> 1.2845112 | F62: =IFERROR(IRR(G62:L62),0) -> 0.067106429 | G62: =-H10 -> -18025 | H62: =-(Financials!G216+Financials!G217)+Financials!G254 -> 2546.2904 | I62: =-(Financials!H216+Financials!H217)+Financials!H254 -> 2354.6973 | J62: =-(Financials!I216+Financials!I217)+Financials!I254 -> 2452.9805 | K62: =-(Financials!J216+Financials!J217)+Financials!J254 -> 2763.2866 | L62: =-(Financials!K216+Financials!K217)+Financials!K254+H46 -> 13036.06
C63: Senior Note | E63: =IFERROR(SUM(H63:L63)/-G63,"NM") -> NM | F63: =IFERROR(IRR(G63:L63),0) -> 0 | G63: =-H11 -> 0 | H63: =Financials!G255+Financials!G224 -> 0 | I63: =Financials!H255+Financials!H224 -> 0 | J63: =Financials!I255+Financials!I224 -> 0 | K63: =Financials!J255+Financials!J224 -> 0 | L63: =Financials!K255+Financials!K224+H47 -> 0
C64: Sub Note at exit EBITDA multiple of:
C65: =$H$40 -> 21.5 | E65: =IFERROR(SUM(H65:L65)/-G65,"NM") -> NM | F65: =IFERROR(IRR(G65:L65),0) -> 0 | G65: =-$H$12 -> 0 | H65: =Financials!G$230+Financials!G$256 -> 0 | I65: =Financials!H$230+Financials!H$256 -> 0 | J65: =Financials!I$230+Financials!I$256 -> 0 | K65: =Financials!J$230+Financials!J$256 -> 0 | L65: =Financials!K$230+Financials!K$256+H48+H56 -> 0
C66: =$I$40 -> 26.5 | E66: =IFERROR(SUM(H66:L66)/-G66,"NM") -> NM | F66: =IFERROR(IRR(G66:L66),0) -> 0 | G66: =-$H$12 -> 0 | H66: =Financials!G$230+Financials!G$256 -> 0 | I66: =Financials!H$230+Financials!H$256 -> 0 | J66: =Financials!I$230+Financials!I$256 -> 0 | K66: =Financials!J$230+Financials!J$256 -> 0 | L66: =Financials!K$230+Financials!K$256+I48+I56 -> 0
C67: =$J$40 -> 31.5 | E67: =IFERROR(SUM(H67:L67)/-G67,"NM") -> NM | F67: =IFERROR(IRR(G67:L67),0) -> 0 | G67: =-$H$12 -> 0 | H67: =Financials!G$230+Financials!G$256 -> 0 | I67: =Financials!H$230+Financials!H$256 -> 0 | J67: =Financials!I$230+Financials!I$256 -> 0 | K67: =Financials!J$230+Financials!J$256 -> 0 | L67: =Financials!K$230+Financials!K$256+J48+J56 -> 0
C68: =$K$40 -> 36.5 | E68: =IFERROR(SUM(H68:L68)/-G68,"NM") -> NM | F68: =IFERROR(IRR(G68:L68),0) -> 0 | G68: =-$H$12 -> 0 | H68: =Financials!G$230+Financials!G$256 -> 0 | I68: =Financials!H$230+Financials!H$256 -> 0 | J68: =Financials!I$230+Financials!I$256 -> 0 | K68: =Financials!J$230+Financials!J$256 -> 0 | L68: =Financials!K$230+Financials!K$256+K48+K56 -> 0
C69: =$L$40 -> 41.5 | E69: =IFERROR(SUM(H69:L69)/-G69,"NM") -> NM | F69: =IFERROR(IRR(G69:L69),0) -> 0 | G69: =-$H$12 -> 0 | H69: =Financials!G$230+Financials!G$256 -> 0 | I69: =Financials!H$230+Financials!H$256 -> 0 | J69: =Financials!I$230+Financials!I$256 -> 0 | K69: =Financials!J$230+Financials!J$256 -> 0 | L69: =Financials!K$230+Financials!K$256+L48+L56 -> 0
C70: Preferred Stock at exit EBITDA multiple of:
C71: =$H$40 -> 21.5 | E71: =IFERROR(SUM(H71:L71)/-G71,"NM") -> NM | F71: =IFERROR(IRR(G71:L71),0) -> 0 | G71: =-$H$13 -> 0 | H71: =Financials!G$239 -> 0 | I71: =Financials!H$239 -> 0 | J71: =Financials!I$239 -> 0 | K71: =Financials!J$239 -> 0 | L71: =Financials!$K$239+Financials!$K$238+LBO!H55 -> 0
C72: =$I$40 -> 26.5 | E72: =IFERROR(SUM(H72:L72)/-G72,"NM") -> NM | F72: =IFERROR(IRR(G72:L72),0) -> 0 | G72: =-$H$13 -> 0 | H72: =Financials!G$239 -> 0 | I72: =Financials!H$239 -> 0 | J72: =Financials!I$239 -> 0 | K72: =Financials!J$239 -> 0 | L72: =Financials!$K$239+Financials!$K$238+I55 -> 0
C73: =$J$40 -> 31.5 | E73: =IFERROR(SUM(H73:L73)/-G73,"NM") -> NM | F73: =IFERROR(IRR(G73:L73),0) -> 0 | G73: =-$H$13 -> 0 | H73: =Financials!G$239 -> 0 | I73: =Financials!H$239 -> 0 | J73: =Financials!I$239 -> 0 | K73: =Financials!J$239 -> 0 | L73: =Financials!$K$239+Financials!$K$238+J55 -> 0
C74: =$K$40 -> 36.5 | E74: =IFERROR(SUM(H74:L74)/-G74,"NM") -> NM | F74: =IFERROR(IRR(G74:L74),0) -> 0 | G74: =-$H$13 -> 0 | H74: =Financials!G$239 -> 0 | I74: =Financials!H$239 -> 0 | J74: =Financials!I$239 -> 0 | K74: =Financials!J$239 -> 0 | L74: =Financials!$K$239+Financials!$K$238+K55 -> 0
C75: =$L$40 -> 41.5 | E75: =IFERROR(SUM(H75:L75)/-G75,"NM") -> NM | F75: =IFERROR(IRR(G75:L75),0) -> 0 | G75: =-$H$13 -> 0 | H75: =Financials!G$239 -> 0 | I75: =Financials!H$239 -> 0 | J75: =Financials!I$239 -> 0 | K75: =Financials!J$239 -> 0 | L75: =Financials!$K$239+Financials!$K$238+L55 -> 0
C76: PIF Rollover at exit EBITDA multiple of:
C77: =$H$40 -> 21.5 | E77: =IFERROR(SUM(H77:L77)/-G77,"NM") -> 1.7885521 | F77: =IFERROR(IRR(G77:L77),0) -> 0.12331179 | G77: =-$H$14 -> -5227.25 | H77: 0 | I77: 0 | J77: 0 | K77: 0 | L77: {=TRANSPOSE(H54:L54)} -> 9349.2088
C78: =$I$40 -> 26.5 | E78: =IFERROR(SUM(H78:L78)/-G78,"NM") -> 2.268161 | F78: =IFERROR(IRR(G78:L78),0) -> 0.17797148 | G78: =-$H$14 -> -5227.25 | H78: 0 | I78: 0 | J78: 0 | K78: 0 | L78: 11856.245
C79: =$J$40 -> 31.5 | E79: =IFERROR(SUM(H79:L79)/-G79,"NM") -> 2.7477699 | F79: =IFERROR(IRR(G79:L79),0) -> 0.2240413 | G79: =-$H$14 -> -5227.25 | H79: 0 | I79: 0 | J79: 0 | K79: 0 | L79: 14363.28
C80: =$K$40 -> 36.5 | E80: =IFERROR(SUM(H80:L80)/-G80,"NM") -> 3.2273788 | F80: =IFERROR(IRR(G80:L80),0) -> 0.2640667 | G80: =-$H$14 -> -5227.25 | H80: 0 | I80: 0 | J80: 0 | K80: 0 | L80: 16870.316
C81: =$L$40 -> 41.5 | E81: =IFERROR(SUM(H81:L81)/-G81,"NM") -> 3.7069878 | F81: =IFERROR(IRR(G81:L81),0) -> 0.29958362 | G81: =-$H$14 -> -5227.25 | H81: 0 | I81: 0 | J81: 0 | K81: 0 | L81: 19377.352
C82: Sponsor's Equity at exit EBITDA multiple of:
C83: =$H$40 -> 21.5 | E83: =IFERROR(SUM(H83:L83)/-G83,"NM") -> 1.7885521 | F83: =IFERROR(IRR(G83:L83),0) -> 0.12331179 | G83: =-$H$15 -> -31323.536 | H83: 0 | I83: 0 | J83: 0 | K83: 0 | L83: {=TRANSPOSE(H53:L53)} -> 56023.776
C84: =$I$40 -> 26.5 | E84: =IFERROR(SUM(H84:L84)/-G84,"NM") -> 2.268161 | F84: =IFERROR(IRR(G84:L84),0) -> 0.17797148 | G84: =-$H$15 -> -31323.536 | H84: 0 | I84: 0 | J84: 0 | K84: 0 | L84: 71046.823
C85: =$J$40 -> 31.5 | E85: =IFERROR(SUM(H85:L85)/-G85,"NM") -> 2.7477699 | F85: =IFERROR(IRR(G85:L85),0) -> 0.2240413 | G85: =-$H$15 -> -31323.536 | H85: 0 | I85: 0 | J85: 0 | K85: 0 | L85: 86069.871
C86: =$K$40 -> 36.5 | E86: =IFERROR(SUM(H86:L86)/-G86,"NM") -> 3.2273788 | F86: =IFERROR(IRR(G86:L86),0) -> 0.2640667 | G86: =-$H$15 -> -31323.536 | H86: 0 | I86: 0 | J86: 0 | K86: 0 | L86: 101092.92
C87: =$L$40 -> 41.5 | E87: =IFERROR(SUM(H87:L87)/-G87,"NM") -> 3.7069878 | F87: =IFERROR(IRR(G87:L87),0) -> 0.29958362 | G87: =-$H$15 -> -31323.536 | H87: 0 | I87: 0 | J87: 0 | K87: 0 | L87: 116115.97
B90: x | C90: RETURNS SUMMARY
C91: SUMMARY AT 31.5x EXIT EBITDA MULTIPLE | G91: Financing | H91: % of Total Capital | I91: % FD Ownership | J91: Cash-on-cash | K91: Expected IRR
C93: Revolver | G93: =H9 -> 0 | H93: =G93/$G$100 -> 0 | J93: =E61 -> NM | K93: =F61 -> 0
C94: Term Loan | G94: =H10 -> 18025 | H94: =G94/$G$100 -> 0.33027467 | J94: =E62 -> 1.2845112 | K94: =F62 -> 0.067106429
C95: Senior Note | G95: =H11 -> 0 | H95: =G95/$G$100 -> 0 | J95: =E63 -> NM | K95: =F63 -> 0
C96: Sub Note | G96: =H12 -> 0 | H96: =G96/$G$100 -> 0 | I96: =G56 -> 0 | J96: =E67 -> NM | K96: =F67 -> 0
C97: Preferred stock | G97: =H13 -> 0 | H97: =G97/$G$100 -> 0 | I97: =G55 -> 0 | J97: =E73 -> NM | K97: =F73 -> 0
C98: PIF rollover | G98: =H14 -> 5227.25 | H98: =G98/$G$100 -> 0.095779655 | I98: =G54 -> 0.14301334 | J98: =E79 -> 2.7477699 | K98: =F79 -> 0.2240413
C99: Sponsor equity | G99: =H15 -> 31323.536 | H99: =G99/$G$100 -> 0.57394567 | I99: =G53 -> 0.85698666 | J99: =E85 -> 2.7477699 | K99: =F85 -> 0.2240413
C100: Total | G100: =SUM(G93:G99) -> 54575.786 | H100: =SUM(H93:H99) -> 1 | I100: =SUM(I93:I99) -> 1
B103: x | C103: SENSITIVITY ANALYSIS
D105: Actual | F105: Offer Price / Share At Various Sponsor Hurdle Rates
C106: Sponsor Hurdle Rate (Minimum IRR) | D106: =K99 -> 0.2240413 | F106: 0.1 | G106: =F106+0.05 -> 0.15 | H106: =G106+0.05 -> 0.2 | I106: =H106+0.05 -> 0.25 | J106: =I106+0.05 -> 0.3 | K106: =J106+0.05 -> 0.35 | L106: =K106+0.05 -> 0.4
C107: Offer value | D107: =D31 -> 54198.419 | F107: =-PV(F106,5,0,$J$53)+SUM($H$8:$H$14)-$L$9-$L$10 -> 76317.501 | G107: =-PV(G106,5,0,$J$53)+SUM($H$8:$H$14)-$L$9-$L$10 -> 65666.82 | H107: =-PV(H106,5,0,$J$53)+SUM($H$8:$H$14)-$L$9-$L$10 -> 57464.434 | I107: =-PV(I106,5,0,$J$53)+SUM($H$8:$H$14)-$L$9-$L$10 -> 51078.258 | J107: =-PV(J106,5,0,$J$53)+SUM($H$8:$H$14)-$L$9-$L$10 -> 46056.002 | K107: =-PV(K106,5,0,$J$53)+SUM($H$8:$H$14)-$L$9-$L$10 -> 42069.626 | L107: =-PV(L106,5,0,$J$53)+SUM($H$8:$H$14)-$L$9-$L$10 -> 38878.235
C108: Diluted shares outstanding | D108: =D32 -> 258.08771 | F108: =$D$108 -> 258.08771 | G108: =$D$108 -> 258.08771 | H108: =$D$108 -> 258.08771 | I108: =$D$108 -> 258.08771 | J108: =$D$108 -> 258.08771 | K108: =$D$108 -> 258.08771 | L108: =$D$108 -> 258.08771
C109: Offer value/share | D109: =D34 -> 210 | F109: =F107/F108 -> 295.70374 | G109: =G107/G108 -> 254.43606 | H109: =H107/H108 -> 222.65467 | I109: =I107/I108 -> 197.91046 | J109: =J107/J108 -> 178.45097 | K109: =K107/K108 -> 163.00515 | L109: =L107/L108 -> 150.63962
C110: % premium/discount | D110: =D35 -> 0.24762357 | F110: =F109/$D$9-1 -> 0.75679502 | G110: =G109/$D$9-1 -> 0.51162108 | H110: =H109/$D$9-1 -> 0.32280577 | I110: =I109/$D$9-1 -> 0.17579885 | J110: =J109/$D$9-1 -> 0.060188729 | K110: =K109/$D$9-1 -> -0.031575863 | L110: =L109/$D$9-1 -> -0.10504026
C112: Enterprise Value | D112: =D26 -> 53834.419 | F112: =F107-$D$13-$D$14 -> 75953.501 | G112: =G107-$D$13-$D$14 -> 65302.82 | H112: =H107-$D$13-$D$14 -> 57100.434 | I112: =I107-$D$13-$D$14 -> 50714.258 | J112: =J107-$D$13-$D$14 -> 45692.002 | K112: =K107-$D$13-$D$14 -> 41705.626 | L112: =L107-$D$13-$D$14 -> 38514.235
C113: EV/LTM EBITDA multiple | D113: =D25 -> 20.906571 | F113: =F112/$D$12 -> 29.496505 | G113: =G112/$D$12 -> 25.360319 | H113: =H112/$D$12 -> 22.174926 | I113: =I112/$D$12 -> 19.694858 | J113: =J112/$D$12 -> 17.744467 | K113: =K112/$D$12 -> 16.19636 | L113: =L112/$D$12 -> 14.956985
C116: Highlight IRR > | F116: Sponsor IRR At Various Leverage And Initial EBITDA Multiple Sensitivity
C117: 0.25 | F117: EXPLICIT EBITDA (APPROACH 1) MUST BE SELECTED FOR DATA TABLE TO APPEAR
G119: Term loan/LTM EBITDA
G120: =K99 -> 0.2240413 | H120: 5 | I120: =H120+2 -> 7 | J120: =I120+2 -> 9 | K120: =J120+2 -> 11 | L120: =K120+2 -> 13
F121: Initial | G121: 15 | H121: 0.20786329 | I121: 0.2240413 | J121: 0.24420046 | K121: 0.27011341 | L121: 0.30486689
F122: EBITDA | G122: =G121+3 -> 18 | H122: 0.20786329 | I122: 0.2240413 | J122: 0.24420046 | K122: 0.27011341 | L122: 0.30486689
F123: Multiple: | G123: =G122+3 -> 21 | H123: 0.20786329 | I123: 0.2240413 | J123: 0.24420046 | K123: 0.27011341 | L123: 0.30486689
G124: =G123+3 -> 24 | H124: 0.20786329 | I124: 0.2240413 | J124: 0.24420046 | K124: 0.27011341 | L124: 0.30486689
...

Sheet Financials
C2: Financial Statement Model
C3: In Millions, expect per share data
C5: Circ Breaker (Off = 1, On = 0) | D5: 1
C6: Latest Fiscal Year End | D6: 45747
C7: Shares outstanding (millions) | D7: 250.25371
B9: x | C9: INCOME STATEMENT
C10: Fiscal Year | D10: 2023 | E10: 2024 | F10: 2025 | G10: 2026 | H10: 2027 | I10: 2028 | J10: 2029 | K10: 2030
C11: End Date | D11: 45016 | E11: =EOMONTH(D11,12) -> 45382 | F11: =EOMONTH(E11,12) -> 45747 | G11: =EOMONTH(F11,12) -> 46112 | H11: =EOMONTH(G11,12) -> 46477 | I11: =EOMONTH(H11,12) -> 46843 | J11: =EOMONTH(I11,12) -> 47208 | K11: =EOMONTH(J11,12) -> 47573
C13: Revenue | D13: 7426 | E13: 7562 | F13: 7463 | G13: 8092.11 | H13: 8412.18 | I13: 8872.86 | J13: 9809.67 | K13: 10448
C14: Cost of revenue | D14: -1792 | E14: -1710 | F14: -1543 | G14: =G15-G13 -> -1818.5622 | H14: =H15-H13 -> -1890.4924 | I14: =I15-I13 -> -1994.0223 | J14: =J15-J13 -> -2204.5542 | K14: =K15-K13 -> -2348.0078
C15: Gross profit | D15: =SUM(D13:D14) -> 5634 | E15: =SUM(E13:E14) -> 5852 | F15: =SUM(F13:F14) -> 5920 | G15: =G13*G42 -> 6273.5478 | H15: =H13*H42 -> 6521.6876 | I15: =I13*I42 -> 6878.8377 | J15: =J13*J42 -> 7605.1158 | K15: =K13*K42 -> 8099.9922
C17: Research and development | D17: -2328 | E17: -2420 | F17: -2569 | G17: =-G44*G13 -> -2637.3423 | H17: =-H44*H13 -> -2741.658 | I17: =-I44*I13 -> -2891.8006 | J17: =-J44*J13 -> -3197.1213 | K17: =-K44*K13 -> -3405.1628
C18: Marketing and sales | D18: -978 | E18: -1019 | F18: -962 | G18: =-G45*G13 -> -1066.418 | H18: =-H45*H13 -> -1108.5984 | I18: =-I45*I13 -> -1169.3091 | J18: =-J45*J13 -> -1292.7665 | K18: =-K45*K13 -> -1376.8887
C19: General and administrative | D19: -727 | E19: -691 | F19: -745 | G19: =-G46*G13 -> -779.81782 | H19: =-H46*H13 -> -810.66222 | I19: =-I46*I13 -> -855.05688 | J19: =-J46*J13 -> -945.33508 | K19: =-K46*K13 -> -1006.8495
C20: Amortization and impairment of intangible assets | D20: -158 | E20: -142 | F20: -67 | G20: =G189 -> -72.647912 | H20: =H189 -> -75.52138 | I20: =I189 -> -79.657191 | J20: =J189 -> -88.067518 | K20: =K189 -> -93.798204
C21: Deal-related D&A | G21: =-('Pro Forma'!$D$15+'Pro Forma'!$D$22) -> -38.09 | H21: =-('Pro Forma'!$D$15+'Pro Forma'!$D$22) -> -38.09 | I21: =-('Pro Forma'!$D$15+'Pro Forma'!$D$22) -> -38.09 | J21: =-('Pro Forma'!$D$15+'Pro Forma'!$D$22) -> -38.09 | K21: =-('Pro Forma'!$D$15+'Pro Forma'!$D$22) -> -38.09
C22: Restructuring | D22: -111 | E22: -62 | F22: -57 | G22: =F22 -> -57 | H22: =G22 -> -57 | I22: =H22 -> -57 | J22: =I22 -> -57 | K22: =J22 -> -57
C23: Operating income (EBIT) | D23: =D15+SUM(D17:D22) -> 1332 | E23: =E15+SUM(E17:E22) -> 1518 | F23: =F15+SUM(F17:F22) -> 1520 | G23: =G15+SUM(G17:G22) -> 1622.2318 | H23: =H15+SUM(H17:H22) -> 1690.1576 | I23: =I15+SUM(I17:I22) -> 1787.9239 | J23: =J15+SUM(J17:J22) -> 1986.7354 | K23: =K15+SUM(K17:K22) -> 2122.2029
C25: Interest income | D25: 49 | E25: 126 | F25: 125 | G25: =G201 -> 9.0744102 | H25: =H201 -> 9.0744102 | I25: =I201 -> 9.0744102 | J25: =J201 -> 9.0744102 | K25: =K201 -> 9.0744102
C26: Interest expense | D26: -58 | E26: -58 | F26: -58 | G26: =-SUM(G253:G257)+G243 -> -1286.196 | H26: =-SUM(H253:H257)+H243 -> -1178.2191 | I26: =-SUM(I253:I257)+I243 -> -1057.9559 | J26: =-SUM(J253:J257)+J243 -> -958.20671 | K26: =-SUM(K253:K257)+K243 -> -840.86202
C27: Other income (expense) | D27: 3 | E27: 3 | F27: 18 | G27: =F27 -> 18 | H27: =G27 -> 18 | I27: =H27 -> 18 | J27: =I27 -> 18 | K27: =J27 -> 18
C28: Income before provision for income taxes | D28: =D23+SUM(D25:D27) -> 1326 | E28: =E23+SUM(E25:E27) -> 1589 | F28: =F23+SUM(F25:F27) -> 1605 | G28: =G23+SUM(G25:G27) -> 363.11025 | H28: =H23+SUM(H25:H27) -> 539.0129 | I28: =I23+SUM(I25:I27) -> 757.04246 | J28: =J23+SUM(J25:J27) -> 1055.6031 | K28: =K23+SUM(K25:K27) -> 1308.4153
C30: Provision for income taxes | D30: -524 | E30: -316 | F30: -484 | G30: =-G48*G28 -> -108.40031 | H30: =-H48*H28 -> -160.91301 | I30: =-I48*I28 -> -226.00198 | J30: =-J48*J28 -> -315.13212 | K30: =-K48*K28 -> -390.60484
C31: Net income | D31: =D28+D30 -> 802 | E31: =E28+E30 -> 1273 | F31: =F28+F30 -> 1121 | G31: =G28+G30 -> 254.70994 | H31: =H28+H30 -> 378.09988 | I31: =I28+I30 -> 531.04048 | J31: =J28+J30 -> 740.47099 | K31: =K28+K30 -> 917.81048
C33: EBIT (GAAP) | D33: =D23 -> 1332 | E33: =E23 -> 1518 | F33: =F23 -> 1520 | G33: =G23 -> 1622.2318 | H33: =H23 -> 1690.1576 | I33: =I23 -> 1787.9239 | J33: =J23 -> 1986.7354 | K33: =K23 -> 2122.2029
C34: Depreciation and amortization | D34: 536 | E34: 404 | F34: 356 | G34: =G181-G189 -> 320.17385 | H34: =H181-H189 -> 293.02888 | I34: =I181-I189 -> 301.81066 | J34: =J181-J189 -> 339.57686 | K34: =K181-K189 -> 389.94092
C35: Stock-based compensation | D35: 548 | E35: 584 | F35: 642 | G35: =F35*(1+G41) -> 696.1188 | H35: =G35*(1+H41) -> 723.65263 | I35: =H35*(1+I41) -> 763.28234 | J35: =I35*(1+J41) -> 843.87085 | K35: =J35*(1+K41) -> 898.7828
C36: Deal-related D&A | G36: =-G21 -> 38.09 | H36: =-H21 -> 38.09 | I36: =-I21 -> 38.09 | J36: =-J21 -> 38.09 | K36: =-K21 -> 38.09
C37: Restructuring | D37: =-D22 -> 111 | E37: =-E22 -> 62 | F37: =-F22 -> 57 | G37: =-G22 -> 57 | H37: =-H22 -> 57 | I37: =-I22 -> 57 | J37: =-J22 -> 57 | K37: =-K22 -> 57
C38: EBITDA | D38: =SUM(D33:D37) -> 2527 | E38: =SUM(E33:E37) -> 2568 | F38: =SUM(F33:F37) -> 2575 | G38: =SUM(G33:G37) -> 2733.6145 | H38: =SUM(H33:H37) -> 2801.9291 | I38: =SUM(I33:I37) -> 2948.107 | J38: =SUM(J33:J37) -> 3265.2731 | K38: =SUM(K33:K37) -> 3506.0166
C40: Growth rates and margins
C41: Revenue growth % | E41: =E13/D13-1 -> 0.018314032 | F41: =F13/E13-1 -> -0.013091775 | G41: =G13/F13-1 -> 0.0842972 | H41: =H13/G13-1 -> 0.039553343 | I41: =I13/H13-1 -> 0.05476345 | J41: =J13/I13-1 -> 0.10558151 | K41: =K13/J13-1 -> 0.065071506
C42: Gross margin % | D42: =D15/D13 -> 0.7586857 | E42: =E15/E13 -> 0.77386935 | F42: =F15/F13 -> 0.79324668 | G42: =AVERAGE(D42:F42) -> 0.77526724 | H42: =G42 -> 0.77526724 | I42: =H42 -> 0.77526724 | J42: =I42 -> 0.77526724 | K42: =J42 -> 0.77526724
C44: Research and development % of sales | D44: =-D17/D13 -> 0.31349313 | E44: =-E17/E13 -> 0.32002116 | F44: =-F17/F13 -> 0.34423154 | G44: =AVERAGE(D44:F44) -> 0.32591528 | H44: =G44 -> 0.32591528 | I44: =H44 -> 0.32591528 | J44: =I44 -> 0.32591528 | K44: =J44 -> 0.32591528
C45: Marketing and sales % of sales | D45: =-D18/D13 -> 0.13169943 | E45: =-E18/E13 -> 0.13475271 | F45: =-F18/F13 -> 0.12890259 | G45: =AVERAGE(D45:F45) -> 0.13178491 | H45: =G45 -> 0.13178491 | I45: =H45 -> 0.13178491 | J45: =I45 -> 0.13178491 | K45: =J45 -> 0.13178491
C46: General and administrative % of sales | D46: =-D19/D13 -> 0.097899273 | E46: =-E19/E13 -> 0.091377942 | F46: =-F19/F13 -> 0.099825807 | G46: =AVERAGE(D46:F46) -> 0.096367674 | H46: =G46 -> 0.096367674 | I46: =H46 -> 0.096367674 | J46: =I46 -> 0.096367674 | K46: =J46 -> 0.096367674
C48: Tax rate | D48: =-D30/D28 -> 0.39517345 | E48: =-E30/E28 -> 0.19886721 | F48: =-F30/F28 -> 0.30155763 | G48: =AVERAGE(D48:F48) -> 0.29853277 | H48: =G48 -> 0.29853277 | I48: =H48 -> 0.29853277 | J48: =I48 -> 0.29853277 | K48: =J48 -> 0.29853277
B51: x | C51: HISTORICAL BALANCE SHEET
C52: Fiscal Year | D52: 2023 | E52: 2024 | F52: 2025
C53: End Date | D53: 45016 | E53: =EOMONTH(D53,12) -> 45382 | F53: =EOMONTH(E53,12) -> 45747
C55: Cash and cash equivalents | D55: 2767 | E55: 3262 | F55: 2248
C56: Receivables | D56: 684 | E56: 565 | F56: 679
C57: Other current assets | D57: 518 | E57: 420 | F57: 349
C58: Property and equipment | D58: 549 | E58: 578 | F58: 586
C59: Goodwill | D59: 5380 | E59: 5379 | F59: 5376
C60: Acquisition-related intangibles | D60: 618 | E60: 400 | F60: 293
C61: Deferred income taxes | D61: 2462 | E61: 2380 | F61: 2420
C62: Other assets | D62: 481 | E62: 436 | F62: 417
C63: Total assets | D63: =SUM(D55:D62) -> 13459 | E63: =SUM(E55:E62) -> 13420 | F63: =SUM(F55:F62) -> 12368
C65: Accounts payable, accrued and other current liabilities | D65: 1384 | E65: 1276 | F65: 1359
C66: Deferred revenue | D66: 1901 | E66: 1814 | F66: 1700
C67: Debt | D67: 1880 | E67: 1882 | F67: 1884
C68: Income tax obligations | D68: 608 | E68: 497 | F68: 594
C69: Other liabilities | D69: 393 | E69: 438 | F69: 445
C70: Total liabilities | D70: =SUM(D65:D69) -> 6166 | E70: =SUM(E65:E69) -> 5907 | F70: =SUM(F65:F69) -> 5982
C72: Common stock | D72: 3 | E72: 3 | F72: 3
C73: Retained earnings | D73: 7357 | E73: 7582 | F73: 6470
C74: Accumulated other comprehensive income | D74: -67 | E74: -72 | F74: -87
C75: Total equity | D75: =SUM(D72:D74) -> 7293 | E75: =SUM(E72:E74) -> 7513 | F75: =SUM(F72:F74) -> 6386
C77: Balance check | D77: =D63-D70-D75 -> 0 | E77: =E63-E70-E75 -> 0 | F77: =F63-F70-F75 -> 0
B80: x | C80: CASH FLOW STATEMENT
C81: Fiscal Year | D81: 2023 | E81: 2024 | F81: 2025 | G81: 2026 | H81: 2027 | I81: 2028 | J81: 2029 | K81: 2030
C82: End Date | D82: 45016 | E82: =EOMONTH(D82,12) -> 45382 | F82: =EOMONTH(E82,12) -> 45747 | G82: =EOMONTH(F82,12) -> 46112 | H82: =EOMONTH(G82,12) -> 46477 | I82: =EOMONTH(H82,12) -> 46843 | J82: =EOMONTH(I82,12) -> 47208 | K82: =EOMONTH(J82,12) -> 47573
C84: Net income | G84: =G31 -> 254.70994 | H84: =H31 -> 378.09988 | I84: =I31 -> 531.04048 | J84: =J31 -> 740.47099 | K84: =K31 -> 917.81048
C85: Depreciation and amortization | G85: =G181-G189 -> 320.17385 | H85: =H181-H189 -> 293.02888 | I85: =I181-I189 -> 301.81066 | J85: =J181-J189 -> 339.57686 | K85: =K181-K189 -> 389.94092
C86: Deal-related D&A | G86: =-G21 -> 38.09 | H86: =-H21 -> 38.09 | I86: =-I21 -> 38.09 | J86: =-J21 -> 38.09 | K86: =-K21 -> 38.09
C87: Stock-based compensation | G87: =G35 -> 696.1188 | H87: =H35 -> 723.65263 | I87: =I35 -> 763.28234 | J87: =J35 -> 843.87085 | K87: =K35 -> 898.7828
C88: Changes in receivables | G88: =F120-G120 -> -57.237798 | H88: =G120-H120 -> -29.120666 | I88: =H120-I120 -> -41.91367 | J88: =I120-J120 -> -85.233015 | K88: =J120-K120 -> -58.076654
C89: Changes in other current assets | G89: =F130-G130 -> -29.419723 | H89: =G130-H130 -> -14.967765 | I89: =H130-I130 -> -21.543256 | J89: =I130-J130 -> -43.809016 | K89: =J130-K130 -> -29.850887
C90: Changes in accounts payable, accrued & other current liabilities | G90: =G140-F140 -> 242.70189 | H90: =H140-G140 -> 63.352664 | I90: =I140-H140 -> 91.184132 | J90: =J140-I140 -> 185.42634 | K90: =K140-J140 -> 126.34707
C91: Changes in deferred income taxes | G91: 0 | H91: 0 | I91: 0 | J91: 0 | K91: 0
C92: Changes in deferred revenue | G92: =G150-F150 -> 143.30524 | H92: =H150-G150 -> 72.908884 | I92: =I150-H150 -> 104.9385 | J92: =J150-I150 -> 213.39636 | K92: =K150-J150 -> 145.40547
C93: Income tax obligations | G93: ='Pro Forma'!E31-'Pro Forma'!H17 -> -11.371113 | H93: ='Pro Forma'!F31-'Pro Forma'!E31 -> -11.371113 | I93: ='Pro Forma'!G31-'Pro Forma'!F31 -> -11.371113 | J93: ='Pro Forma'!H31-'Pro Forma'!G31 -> -11.371113 | K93: ='Pro Forma'!I31-'Pro Forma'!H31 -> -11.371113
C94: Addback of PIK interest | G94: =G257 -> 0 | H94: =H257 -> 0 | I94: =I257 -> 0 | J94: =J257 -> 0 | K94: =K257 -> 0
C95: Financing fee amortization | G95: =-G243 -> 38.625 | H95: =-H243 -> 38.625 | I95: =-I243 -> 38.625 | J95: =-J243 -> 38.625 | K95: =-K243 -> 38.625
C96: Cash flows from operating activities | G96: =SUM(G84:G95) -> 1635.6961 | H96: =SUM(H84:H95) -> 1552.2984 | I96: =SUM(I84:I95) -> 1794.1431 | J96: =SUM(J84:J95) -> 2259.0433 | K96: =SUM(K84:K95) -> 2455.7031
C98: Capital expenditures | G98: =-G162 -> -239.62968 | H98: =-H162 -> -249.10784 | I98: =-I162 -> -262.74984 | J98: =-J162 -> -290.49137 | K98: =-K162 -> -309.39408
C99: Purchases of intangible assets | G99: =-G188 -> -97.346992 | H99: =-H188 -> -88.087441 | I99: =-I188 -> -97.74365 | J99: =-J188 -> -124.84701 | K99: =-K188 -> -118.85926
C100: Cash flows from investing activities | G100: =SUM(G98:G99) -> -336.97667 | H100: =SUM(H98:H99) -> -337.19528 | I100: =SUM(I98:I99) -> -360.49349 | J100: =SUM(J98:J99) -> -415.33837 | K100: =SUM(K98:K99) -> -428.25334
C102: Required debt repayments | G102: =G216+G224+G230 -> -901.25 | H102: =H216+H224+H230 -> -901.25 | I102: =I216+I224+I230 -> -901.25 | J102: =J216+J224+J230 -> -901.25 | K102: =K216+K224+K230 -> -901.25
C103: Preferred dividends paid | G103: =-G239 -> 0 | H103: =-H239 -> 0 | I103: =-I239 -> 0 | J103: =-J239 -> 0 | K103: =-K239 -> 0
C104: Pre-revolver cash flows | G104: =SUM(G102:G103)+G100+G96 -> 397.46941 | H104: =SUM(H102:H103)+H100+H96 -> 313.85312 | I104: =SUM(I102:I103)+I100+I96 -> 532.39958 | J104: =SUM(J102:J103)+J100+J96 -> 942.45488 | K104: =SUM(K102:K103)+K100+K96 -> 1126.1997
C105: Revolver | G105: =G211 -> 0 | H105: =H211 -> 0 | I105: =I211 -> 0 | J105: =J211 -> 0 | K105: =K211 -> 0
C106: Post-revolver cash flows | G106: =SUM(G104:G105) -> 397.46941 | H106: =SUM(H104:H105) -> 313.85312 | I106: =SUM(I104:I105) -> 532.39958 | J106: =SUM(J104:J105) -> 942.45488 | K106: =SUM(K104:K105) -> 1126.1997
C107: Discretionary debt paydown | G107: =G217 -> -397.46941 | H107: =H217 -> -313.85312 | I107: =I217 -> -532.39958 | J107: =J217 -> -942.45488 | K107: =K217 -> -1126.1997
C108: Cash flows from financing activities | G108: =SUM(G102,G103,G105,G107) -> -1298.7194 | H108: =SUM(H102,H103,H105,H107) -> -1215.1031 | I108: =SUM(I102,I103,I105,I107) -> -1433.6496 | J108: =SUM(J102,J103,J105,J107) -> -1843.7049 | K108: =SUM(K102,K103,K105,K107) -> -2027.4497
C110: Net change in cash | G110: =G96+G100+G108 -> 0 | H110: =H96+H100+H108 -> 0 | I110: =I96+I100+I108 -> 0 | J110: =J96+J100+J108 -> 0 | K110: =K96+K100+K108 -> 0
B113: x | C113: Working Capital
C114: Fiscal Year | D114: 2023 | E114: 2024 | F114: 2025 | G114: 2026 | H114: 2027 | I114: 2028 | J114: 2029 | K114: 2030
C115: End Date | D115: 45016 | E115: =EOMONTH(D115,12) -> 45382 | F115: =EOMONTH(E115,12) -> 45747 | G115: =EOMONTH(F115,12) -> 46112 | H115: =EOMONTH(G115,12) -> 46477 | I115: =EOMONTH(H115,12) -> 46843 | J115: =EOMONTH(I115,12) -> 47208 | K115: =EOMONTH(J115,12) -> 47573
C117: Receivables
C118: Beginning of period | E118: =D120 -> 684 | F118: =E120 -> 565 | G118: =F120 -> 679 | H118: =G120 -> 736.2378 | I118: =H120 -> 765.35846 | J118: =I120 -> 807.27213 | K118: =J120 -> 892.50515
C119: Increase/Decrease | E119: =E120-E118 -> -119 | F119: =F120-F118 -> 114 | G119: =G120-G118 -> 57.237798 | H119: =H120-H118 -> 29.120666 | I119: =I120-I118 -> 41.91367 | J119: =J120-J118 -> 85.233015 | K119: =K120-K118 -> 58.076654
C120: End of period | D120: =D56 -> 684 | E120: =E56 -> 565 | F120: =F56 -> 679 | G120: =IF($D$122=1,F120*(1+G124),2*G13*G125/365-G118) -> 736.2378 | H120: =IF($D$122=1,G120*(1+H124),2*H13*H125/365-H118) -> 765.35846 | I120: =IF($D$122=1,H120*(1+I124),2*I13*I125/365-I118) -> 807.27213 | J120: =IF($D$122=1,I120*(1+J124),2*J13*J125/365-J118) -> 892.50515 | K120: =IF($D$122=1,J120*(1+K124),2*K13*K125/365-K118) -> 950.5818
C122: A/R forecasting approach (1=grow with rev, 2=DSO) | D122: 1
C124: Grow in line with revenue (1) | E124: =E41 -> 0.018314032 | F124: =F41 -> -0.013091775 | G124: =G41 -> 0.0842972 | H124: =H41 -> 0.039553343 | I124: =I41 -> 0.05476345 | J124: =J41 -> 0.10558151 | K124: =K41 -> 0.065071506
C125: DSO Assumption (2) | E125: =AVERAGE(D56:E56)/E13*365 -> 30.14315 | F125: =AVERAGE(E56:F56)/F13*365 -> 30.420742 | G125: =F125 -> 30.420742 | H125: =G125 -> 30.420742 | I125: =H125 -> 30.420742 | J125: =I125 -> 30.420742 | K125: =J125 -> 30.420742
C127: Other current assets
C128: Beginning of period | E128: =D130 -> 518 | F128: =E130 -> 420 | G128: =F130 -> 349 | H128: =G130 -> 378.41972 | I128: =H130 -> 393.38749 | J128: =I130 -> 414.93074 | K128: =J130 -> 458.73976
C129: Increase/Decrease | E129: =E130-E128 -> -98 | F129: =F130-F128 -> -71 | G129: =G130-G128 -> 29.419723 | H129: =H130-H128 -> 14.967765 | I129: =I130-I128 -> 21.543256 | J129: =J130-J128 -> 43.809016 | K129: =K130-K128 -> 29.850887
...

Sheet Pro Forma
C2: Purchase Price Allocation & Pro Forma Adjustments
C3: In Millions, expect per share data
C5: Tax Structure | D5: Stock Sale
C6: LBO / Recap | D6: LBO
B8: x | C8: Purchase Price Allocation
C10: Asset Write-ups | F10: Purchase Price Allocation
C11: Book value of PP&E | D11: =E41 -> 586 | F11: Book Value of Total Assets | H11: =E46 -> 12368
C12: % Write-up | D12: 0.2 | F12: Plus: PP&E write ups | H12: =D13 -> 117.2
C13: Asset write-up | D13: =IF($D$6="LBO",D11*D12,0) -> 117.2 | F13: Plus: Intangible asset write ups | H13: =D20 -> 87.9
C14: Useful life | D14: =Financials!D172 -> 5 | F14: Fair Market Value of Assets | H14: =SUM(H11:H13) -> 12573.1
C15: Incremental depreciation expense | D15: =D13/D14 -> 23.44
C16: Incremental deferred tax liabilities | D16: =IF($D$5="Stock Sale",D13*Financials!G48,0) -> 34.98804 | F16: Book Value of Total Liabilities | H16: =E53 -> 5982
F17: Plus: New deferred tax liabilities created | H17: =D16+D23 -> 61.22907
C18: Book value of intangible assets | D18: =E43 -> 293 | F18: Fair Market Value of Liabilities | H18: =SUM(H16:H17) -> 6043.2291
C19: % Write-up | D19: 0.3
C20: Asset write-up | D20: =IF($D$6="LBO",D18*D19,0) -> 87.9 | F20: Equity fair market value | H20: =H14-H18 -> 6529.8709
C21: Useful life | D21: 6 | F21: Offer value | H21: =LBO!D31 -> 54198.419
C22: Incremental amortization expense | D22: =D20/D21 -> 14.65 | F22: Goodwill created in transaction | H22: =H21-H20 -> 47668.548
C23: Incremental deferred tax liabilities | D23: =IF($D$5="Stock Sale",D20*Financials!G48,0) -> 26.24103
C26: Deal-related Accounting Adjustments
E27: 2026 | F27: 2027 | G27: 2028 | H27: 2029 | I27: 2030
E28: 46112 | F28: =EOMONTH(E28,12) -> 46477 | G28: =EOMONTH(F28,12) -> 46843 | H28: =EOMONTH(G28,12) -> 47208 | I28: =EOMONTH(H28,12) -> 47573
C29: PPE | E29: =D13-D15 -> 93.76 | F29: =E29-$D$15 -> 70.32 | G29: =F29-$D$15 -> 46.88 | H29: =G29-$D$15 -> 23.44 | I29: =H29-$D$15 -> 0
C30: Intangible assets | E30: =D20-D22 -> 73.25 | F30: =E30-$D$22 -> 58.6 | G30: =F30-$D$22 -> 43.95 | H30: =G30-$D$22 -> 29.3 | I30: =H30-$D$22 -> 14.65
C31: Deferred tax liabilities | D31: =IF($D$5="Stock Sale",(D15+D22)*Financials!G48,0) -> 11.371113 | E31: =H17-D31 -> 49.857957 | F31: =E31-$D$31 -> 38.486844 | G31: =F31-$D$31 -> 27.115731 | H31: =G31-$D$31 -> 15.744618 | I31: =H31-$D$31 -> 4.373505
B34: x | C34: PRO FORMA BALANCE SHEET ADJUSTMENTS
C35: Fiscal Year | E35: 2025 | F35: Pro Forma Adjustments | I35: Pro Forma
C36: End Date | E36: 45747 | F36: Uses of Funds | G36: Sources of Funds | H36: Accounting | I36: =E36 -> 45747
C38: Cash and cash equivalents | E38: =Financials!F55 -> 2248 | F38: =SUM(F50,F55) -> -51396.536 | G38: =SUM(G50,G55,G56) -> 49348.536 | I38: =SUM(E38:H38) -> 200
C39: Receivables | E39: =Financials!F56 -> 679 | I39: =SUM(E39:H39) -> 679
C40: Other current assets | E40: =Financials!F57 -> 349 | I40: =SUM(E40:H40) -> 349
C41: Property and equipment | E41: =Financials!F58 -> 586 | H41: =D13 -> 117.2 | I41: =SUM(E41:H41) -> 703.2
C42: Goodwill | E42: =Financials!F59 -> 5376 | H42: =H22 -> 47668.548 | I42: =SUM(E42:H42) -> 53044.548
C43: Acquisition-related intangibles | E43: =Financials!F60 -> 293 | H43: =D20 -> 87.9 | I43: =SUM(E43:H43) -> 380.9
C44: Deferred income taxes | E44: =Financials!F61 -> 2420 | I44: =SUM(E44:H44) -> 2420
C45: Other assets | E45: =Financials!F62 -> 417 | I45: =SUM(E45:H45) -> 417
C46: Total assets | E46: =SUM(E38:E45) -> 12368 | I46: =SUM(I38:I45) -> 58193.648
C48: Accounts payable, accrued and other current liabilities | E48: =Financials!F65 -> 1359 | I48: =SUM(E48:H48) -> 1359
C49: Deferred revenue | E49: =Financials!F66 -> 1700 | I49: =SUM(E49:H49) -> 1700
C50: Debt | E50: =Financials!F67 -> 1884 | F50: =-LBO!L9-LBO!J26 -> -2154.375 | G50: =SUM(LBO!H9:H12) -> 18025 | I50: =SUM(E50:H50) -> 17754.625
C51: Income tax obligations | E51: =Financials!F68 -> 594 | H51: =H17 -> 61.22907 | I51: =SUM(E51:H51) -> 655.22907
C52: Other liabilities | E52: =Financials!F69 -> 445 | I52: =SUM(E52:H52) -> 445
C53: Total liabilities | E53: =SUM(E48:E52) -> 5982 | I53: =SUM(I48:I52) -> 21913.854
C55: Equity | E55: =Financials!F75 -> 6386 | F55: =-LBO!L8-LBO!J29+LBO!H14 -> -49242.161 | G55: =LBO!H15 -> 31323.536 | H55: =SUM(H41:H43)-H51 -> 47812.419 | I55: =SUM(E55:H55) -> 36279.794
C56: LBO preferred stock | E56: NM | G56: =LBO!H13 -> 0 | I56: =SUM(F56:H56) -> 0
C57: Total equity | E57: =SUM(E55:E56) -> 6386 | I57: =SUM(I55:I56) -> 36279.794
C59: Balance check | E59: =E46-E53-E57 -> 0 | I59: =I46-I53-I57 -> 0
B62: x | C62: PRO FORMA BALANCE SHEET
C63: Fiscal Year | D63: 2025 | E63: 2026 | F63: 2027 | G63: 2028 | H63: 2029 | I63: 2030
C64: End Date | D64: 45747 | E64: =EOMONTH(D64,12) -> 46112 | F64: =EOMONTH(E64,12) -> 46477 | G64: =EOMONTH(F64,12) -> 46843 | H64: =EOMONTH(G64,12) -> 47208 | I64: =EOMONTH(H64,12) -> 47573
C66: Cash and cash equivalents | D66: =I38 -> 200 | E66: =Financials!G199 -> 200 | F66: =Financials!H199 -> 200 | G66: =Financials!I199 -> 200 | H66: =Financials!J199 -> 200 | I66: =Financials!K199 -> 200
C67: Receivables | D67: =I39 -> 679 | E67: =Financials!G120 -> 736.2378 | F67: =Financials!H120 -> 765.35846 | G67: =Financials!I120 -> 807.27213 | H67: =Financials!J120 -> 892.50515 | I67: =Financials!K120 -> 950.5818
C68: Other current assets | D68: =I40 -> 349 | E68: =Financials!G130 -> 378.41972 | F68: =Financials!H130 -> 393.38749 | G68: =Financials!I130 -> 414.93074 | H68: =Financials!J130 -> 458.73976 | I68: =Financials!K130 -> 488.59065
C69: Property and equipment | D69: =I41 -> 703.2 | E69: =Financials!G164+E29 -> 671.86374 | F69: =Financials!H164+F29 -> 680.02408 | G69: =Financials!I164+G29 -> 697.18045 | H69: =Financials!J164+H29 -> 712.72247 | I69: =Financials!K164+I29 -> 702.53383
C70: Goodwill | D70: =I42 -> 53044.548 | E70: =D70 -> 53044.548 | F70: =E70 -> 53044.548 | G70: =F70 -> 53044.548 | H70: =G70 -> 53044.548 | I70: =H70 -> 53044.548
C71: Acquisition-related intangibles | D71: =I43 -> 380.9 | E71: =Financials!G190+E30 -> 390.94908 | F71: =Financials!H190+F30 -> 388.86514 | G71: =Financials!I190+G30 -> 392.3016 | H71: =Financials!J190+H30 -> 414.43109 | I71: =Financials!K190+I30 -> 424.84215
C72: Deferred income taxes | D72: =I44 -> 2420 | E72: =D72 -> 2420 | F72: =E72 -> 2420 | G72: =F72 -> 2420 | H72: =G72 -> 2420 | I72: =H72 -> 2420
C73: Other assets | D73: =I45 -> 417 | E73: =D73 -> 417 | F73: =E73 -> 417 | G73: =F73 -> 417 | H73: =G73 -> 417 | I73: =H73 -> 417
C74: Total assets | D74: =SUM(D66:D73) -> 58193.648 | E74: =SUM(E66:E73) -> 58259.019 | F74: =SUM(F66:F73) -> 58309.184 | G74: =SUM(G66:G73) -> 58393.233 | H74: =SUM(H66:H73) -> 58559.947 | I74: =SUM(I66:I73) -> 58648.097
C76: Accounts payable, accrued and other current liabilities | D76: =I48 -> 1359 | E76: =Financials!G140 -> 1601.7019 | F76: =Financials!H140 -> 1665.0546 | G76: =Financials!I140 -> 1756.2387 | H76: =Financials!J140 -> 1941.665 | I76: =Financials!K140 -> 2068.0121
C77: Deferred revenue | D77: =I49 -> 1700 | E77: =Financials!G150 -> 1843.3052 | F77: =Financials!H150 -> 1916.2141 | G77: =Financials!I150 -> 2021.1526 | H77: =Financials!J150 -> 2234.549 | I77: =Financials!K150 -> 2379.9544
C78: Debt | D78: =I50 -> 17754.625 | E78: =SUM(Financials!G212,Financials!G218,Financials!G225,Financials!G232)-Financials!G244 -> 16494.531 | F78: =SUM(Financials!H212,Financials!H218,Financials!H225,Financials!H232)-Financials!H244 -> 15318.052 | G78: =SUM(Financials!I212,Financials!I218,Financials!I225,Financials!I232)-Financials!I244 -> 13923.028 | H78: =SUM(Financials!J212,Financials!J218,Financials!J225,Financials!J232)-Financials!J244 -> 12117.948 | I78: =SUM(Financials!K212,Financials!K218,Financials!K225,Financials!K232)-Financials!K244 -> 10129.123
C79: Income tax obligations | D79: =I51 -> 655.22907 | E79: =$E$51+E31 -> 643.85796 | F79: =$E$51+F31 -> 632.48684 | G79: =$E$51+G31 -> 621.11573 | H79: =$E$51+H31 -> 609.74462 | I79: =$E$51+I31 -> 598.37351
C80: Other liabilities | D80: =I52 -> 445 | E80: =D80 -> 445 | F80: =E80 -> 445 | G80: =F80 -> 445 | H80: =G80 -> 445 | I80: =H80 -> 445
C81: Total liabilities | D81: =SUM(D76:D80) -> 21913.854 | E81: =SUM(E76:E80) -> 21028.396 | F81: =SUM(F76:F80) -> 19976.808 | G81: =SUM(G76:G80) -> 18766.535 | H81: =SUM(H76:H80) -> 17348.907 | I81: =SUM(I76:I80) -> 15620.463
C83: Equity | D83: =I55 -> 36279.794 | E83: =D83+Financials!G31-(Financials!G237+Financials!G239)+Financials!G35 -> 37230.623 | F83: =E83+Financials!H31-(Financials!H237+Financials!H239)+Financials!H35 -> 38332.376 | G83: =F83+Financials!I31-(Financials!I237+Financials!I239)+Financials!I35 -> 39626.698 | H83: =G83+Financials!J31-(Financials!J237+Financials!J239)+Financials!J35 -> 41211.04 | I83: =H83+Financials!K31-(Financials!K237+Financials!K239)+Financials!K35 -> 43027.633
C84: LBO preferred stock | D84: =I56 -> 0 | E84: =Financials!G238 -> 0 | F84: =Financials!H238 -> 0 | G84: =Financials!I238 -> 0 | H84: =Financials!J238 -> 0 | I84: =Financials!K238 -> 0
C85: Total equity | D85: =SUM(D83:D84) -> 36279.794 | E85: =SUM(E83:E84) -> 37230.623 | F85: =SUM(F83:F84) -> 38332.376 | G85: =SUM(G83:G84) -> 39626.698 | H85: =SUM(H83:H84) -> 41211.04 | I85: =SUM(I83:I84) -> 43027.633
C87: Balance check | D87: =D74-D81-D85 -> 0 | E87: =E74-E81-E85 -> 0 | F87: =F74-F81-F85 -> 0 | G87: =G74-G81-G85 -> 0 | H87: =H74-H81-H85 -> 0 | I87: =I74-I81-I85 -> 0

Sheet WACC
C2: WACC Analysis
C3: In Millions, expect per share data
C5: INPUTS | F5: BETA CALCULATION
H6: 5-year
C7: Tax rate (5-year average) | D7: 0.20954 | F7: Company Name | G7: Ticker | H7: average tax rate | I7: Levered Beta | J7: Total Debt | K7: Market cap | L7: Unlevered Beta
C8: Risk-free rate | D8: 0.0431 | F8: Roblox Corporation | G8: NYSE: RBLX | H8: 0.088375 | I8: 1.67 | J8: 1764.4 | K8: 79317.6 | L8: =I8/(1+(1-H8)*(J8/K8)) -> 1.6368074
C9: Market risk premium | D9: 0.0418 | F9: Take-Two Interactive Software | G9: NASDAQ: TTWO | H9: 0.14514 | I9: 0.97 | J9: 3511.7 | K9: 42868.7 | L9: =I9/(1+(1-H9)*(J9/K9)) -> 0.90651828
F10: Playtika Holding Corp | G10: NASDAQ: PLTK | H10: 0.3184 | I10: 0.88 | J10: 2541.5 | K10: 1571.9 | L10: =I10/(1+(1-H10)*(J10/K10)) -> 0.41864224
C11: WACC | F11: Playstudios | G11: NASDAQ: MYPS | H11: 0.32333333 | I11: 0.95 | J11: 8.6 | K11: 95.5 | L11: =I11/(1+(1-H11)*(J11/K11)) -> 0.89543621
F12: Average | L12: =AVERAGE(L8:L11) -> 0.96435103
C13: Market risk premium | D13: =D9 -> 0.0418 | F13: EA Avg Tax Rate | L13: =D7 -> 0.20954
C14: Levered Beta | D14: =L16 -> 0.99741028 | F14: Total Debt | L14: =SUM(DCF!I52:I56) -> 1884
C15: Adjusted market risk premium | D15: =D13*D14 -> 0.04169175 | F15: Market cap | L15: =DCF!I72*DCF!D8 -> 43441.324
C16: Add: risk-free rate | D16: =D8 -> 0.0431 | F16: EA Levered Beta | L16: =L12*(1+(1-L13)*(L14/L15)) -> 0.99741028
C17: Cost of Equity | D17: =D15+D16 -> 0.08479175
C18: Equity to total capitalization | D18: =L15/(L15+L14) -> 0.95843383 | F18: WACC Sensitivity
C19: Cost of equity portion | D19: =D17*D18 -> 0.081267281
F20: Pre-tax cost of debt
C21: Cost of debt | D21: =-Financials!F26/Financials!F67 -> 0.030785563 | F21: =D27 -> 0.082278784 | G21: 0.005 | H21: =G21+$N$25 -> 0.015 | I21: =H21+$N$25 -> 0.025 | J21: =I21+$N$25 -> 0.035 | K21: =J21+$N$25 -> 0.045 | L21: =K21+$N$25 -> 0.055
C22: Tax rate | D22: =D7 -> 0.20954 | F22: 0.01 | G22: 0.081306804 | H22: 0.08138585 | I22: 0.081464896 | J22: 0.081543942 | K22: 0.081622988 | L22: 0.081702034
C23: After-tax cost of debt | D23: =D21*(1-D22) -> 0.024334756 | F23: =F22+$N$26 -> 0.025 | G23: 0.081366089 | H23: 0.081563704 | I23: 0.081761319 | J23: 0.081958934 | K23: 0.082156549 | L23: 0.082354164
C24: Debt to total capitalization | D24: =L14/(L15+L14) -> 0.041566168 | F24: =F23+$N$26 -> 0.04 | G24: 0.081425373 | H24: 0.081741557 | I24: 0.082057741 | J24: 0.082373925 | K24: 0.082690109 | L24: 0.083006293
C25: Cost of debt portion | D25: =D23*D24 -> 0.0010115025 | F25: =F24+$N$26 -> 0.055 | G25: 0.081484658 | H25: 0.081919411 | I25: 0.082354164 | J25: 0.082788917 | K25: 0.08322367 | L25: 0.083658423 | N25: 0.01 | O25: Pre-tax cost of debt step
F26: =F25+$N$26 -> 0.07 | G26: 0.081543942 | H26: 0.082097264 | I26: 0.082650586 | J26: 0.083203908 | K26: 0.08375723 | L26: 0.084310552 | N26: 0.015 | O26: Debt to total cap
C27: WACC | D27: =D19+D25 -> 0.082278784 | F27: =F26+$N$26 -> 0.085 | G27: 0.081603227 | H27: 0.082275118 | I27: 0.082947009 | J27: 0.0836189 | K27: 0.084290791 | L27: 0.084962682 | N27: 0.035 | O27: Equity to total cap
N28: 0.01 | O28: Cost of equity step
F29: Cost of Equity
F30: =D27 -> 0.082278784 | G30: 0.06 | H30: =G30+$N$28 -> 0.07 | I30: =H30+$N$28 -> 0.08 | J30: =I30+$N$28 -> 0.09 | K30: =J30+$N$28 -> 0.1 | L30: =K30+$N$28 -> 0.11
F31: 0.8 | G31: 0.049011503 | H31: 0.057011503 | I31: 0.065011503 | J31: 0.073011503 | K31: 0.081011503 | L31: 0.089011503
F32: =F31+$N$27 -> 0.835 | G32: 0.051111503 | H32: 0.059461503 | I32: 0.067811503 | J32: 0.076161503 | K32: 0.084511503 | L32: 0.092861503
F33: =F32+$N$27 -> 0.87 | G33: 0.053211503 | H33: 0.061911503 | I33: 0.070611503 | J33: 0.079311503 | K33: 0.088011503 | L33: 0.096711503
F34: =F33+$N$27 -> 0.905 | G34: 0.055311503 | H34: 0.064361503 | I34: 0.073411503 | J34: 0.082461503 | K34: 0.091511503 | L34: 0.1005615
F35: =F34+$N$27 -> 0.94 | G35: 0.057411503 | H35: 0.066811503 | I35: 0.076211503 | J35: 0.085611503 | K35: 0.095011503 | L35: 0.1044115
F36: =F35+$N$27 -> 0.975 | G36: 0.059511503 | H36: 0.069261503 | I36: 0.079011503 | J36: 0.088761503 | K36: 0.098511503 | L36: 0.1082615

Sheet DCF
C2: Discounted Cash Flow Model
C3: In Millions, expect per share data
C5: Most recent fiscal year end | D5: =Financials!D6 -> 45747 | F5: Discount Rate (WACC) | H5: =WACC!D27 -> 0.082278784
C6: End of first fiscal year | D6: =E12 -> 46112 | F6: Midyear Convention | H6: 1
C7: Valuation date | D7: =LBO!D10 -> 45925
C8: Share price | D8: =LBO!D9 -> 168.32
C9: Potion of first year cash flows | D9: =YEARFRAC(D7,D6) -> 0.51666667
B11: x | C11: Fiscal Year | E11: 2026 | F11: 2027 | G11: 2028 | H11: 2029 | I11: 2030
C12: End Date | E12: 46112 | F12: =EOMONTH(E12,12) -> 46477 | G12: =EOMONTH(F12,12) -> 46843 | H12: =EOMONTH(G12,12) -> 47208 | I12: =EOMONTH(H12,12) -> 47573
C14: Revenue | E14: =Financials!G13 -> 8092.11 | F14: =Financials!H13 -> 8412.18 | G14: =Financials!I13 -> 8872.86 | H14: =Financials!J13 -> 9809.67 | I14: =Financials!K13 -> 10448
C15: Cost of revenue | E15: =Financials!G14 -> -1818.5622 | F15: =Financials!H14 -> -1890.4924 | G15: =Financials!I14 -> -1994.0223 | H15: =Financials!J14 -> -2204.5542 | I15: =Financials!K14 -> -2348.0078
C16: Gross profit | E16: =SUM(E14:E15) -> 6273.5478 | F16: =SUM(F14:F15) -> 6521.6876 | G16: =SUM(G14:G15) -> 6878.8377 | H16: =SUM(H14:H15) -> 7605.1158 | I16: =SUM(I14:I15) -> 8099.9922
C18: Research and development | E18: =Financials!G17 -> -2637.3423 | F18: =Financials!H17 -> -2741.658 | G18: =Financials!I17 -> -2891.8006 | H18: =Financials!J17 -> -3197.1213 | I18: =Financials!K17 -> -3405.1628
C19: Marketing and sales | E19: =Financials!G18 -> -1066.418 | F19: =Financials!H18 -> -1108.5984 | G19: =Financials!I18 -> -1169.3091 | H19: =Financials!J18 -> -1292.7665 | I19: =Financials!K18 -> -1376.8887
C20: General and administrative | E20: =Financials!G19 -> -779.81782 | F20: =Financials!H19 -> -810.66222 | G20: =Financials!I19 -> -855.05688 | H20: =Financials!J19 -> -945.33508 | I20: =Financials!K19 -> -1006.8495
C21: Amortization and impairment of intangible assets | E21: =Financials!G20 -> -72.647912 | F21: =Financials!H20 -> -75.52138 | G21: =Financials!I20 -> -79.657191 | H21: =Financials!J20 -> -88.067518 | I21: =Financials!K20 -> -93.798204
C22: Deal-related D&A | E22: =Financials!G21 -> -38.09 | F22: =Financials!H21 -> -38.09 | G22: =Financials!I21 -> -38.09 | H22: =Financials!J21 -> -38.09 | I22: =Financials!K21 -> -38.09
C23: Restructuring | E23: =Financials!G22 -> -57 | F23: =Financials!H22 -> -57 | G23: =Financials!I22 -> -57 | H23: =Financials!J22 -> -57 | I23: =Financials!K22 -> -57
C24: Operating income (EBIT) | E24: =E16+SUM(E18:E23) -> 1622.2318 | F24: =F16+SUM(F18:F23) -> 1690.1576 | G24: =G16+SUM(G18:G23) -> 1787.9239 | H24: =H16+SUM(H18:H23) -> 1986.7354 | I24: =I16+SUM(I18:I23) -> 2122.2029
C25: Tax expense | E25: =E24*-Financials!G48 -> -484.28935 | F25: =F24*-Financials!H48 -> -504.56743 | G25: =G24*-Financials!I48 -> -533.75388 | H25: =H24*-Financials!J48 -> -593.10562 | I25: =I24*-Financials!K48 -> -633.54711
C26: NOPAT | E26: =SUM(E24:E25) -> 1137.9425 | F26: =SUM(F24:F25) -> 1185.5902 | G26: =SUM(G24:G25) -> 1254.1701 | H26: =SUM(H24:H25) -> 1393.6298 | I26: =SUM(I24:I25) -> 1488.6558
C28: Non cash Add Back
C29: Depreciation and amortization | E29: =Financials!G85 -> 320.17385 | F29: =Financials!H85 -> 293.02888 | G29: =Financials!I85 -> 301.81066 | H29: =Financials!J85 -> 339.57686 | I29: =Financials!K85 -> 389.94092
C30: Deal-related D&A | E30: =Financials!G36 -> 38.09 | F30: =Financials!H36 -> 38.09 | G30: =Financials!I36 -> 38.09 | H30: =Financials!J36 -> 38.09 | I30: =Financials!K36 -> 38.09
C32: Net Working Capital Adjustments
C33: (Increase)/Decrease in receivables | E33: =Financials!G88 -> -57.237798 | F33: =Financials!H88 -> -29.120666 | G33: =Financials!I88 -> -41.91367 | H33: =Financials!J88 -> -85.233015 | I33: =Financials!K88 -> -58.076654
C34: (Increase)/Decrease in other current assets | E34: =Financials!G89 -> -29.419723 | F34: =Financials!H89 -> -14.967765 | G34: =Financials!I89 -> -21.543256 | H34: =Financials!J89 -> -43.809016 | I34: =Financials!K89 -> -29.850887
C35: Increase/(Decrease) in A/P, accured and other current liabilities | E35: =Financials!G90 -> 242.70189 | F35: =Financials!H90 -> 63.352664 | G35: =Financials!I90 -> 91.184132 | H35: =Financials!J90 -> 185.42634 | I35: =Financials!K90 -> 126.34707
C36: Increase/(Decrease) in deferred revenue | E36: =Financials!G92 -> 143.30524 | F36: =Financials!H92 -> 72.908884 | G36: =Financials!I92 -> 104.9385 | H36: =Financials!J92 -> 213.39636 | I36: =Financials!K92 -> 145.40547
C38: Capital Expenditures
C39: Capital Expenditures | E39: =Financials!G98 -> -239.62968 | F39: =Financials!H98 -> -249.10784 | G39: =Financials!I98 -> -262.74984 | H39: =Financials!J98 -> -290.49137 | I39: =Financials!K98 -> -309.39408
C40: Unlevered Free Cash Flow | E40: =E26+SUM(E29:E39) -> 1555.9262 | F40: =F26+SUM(F29:F39) -> 1359.7744 | G40: =G26+SUM(G29:G39) -> 1463.9866 | H40: =H26+SUM(H29:H39) -> 1750.586 | I40: =I26+SUM(I29:I39) -> 1791.1177
C42: Fiscal Year | D42: Val Date | E42: 1 | F42: 2 | G42: 3 | H42: 4 | I42: 5
C43: End Date | D43: =D7 -> 45925 | E43: =IF($H$6=0,E12,AVERAGE(D43,E12)) -> 46018.5 | F43: =IF($H$6=0,F12,AVERAGE(F12,E12)) -> 46294.5 | G43: =IF($H$6=0,G12,AVERAGE(G12,F12)) -> 46660 | H43: =IF($H$6=0,H12,AVERAGE(H12,G12)) -> 47025.5 | I43: =IF($H$6=0,I12,AVERAGE(I12,H12)) -> 47390.5
C45: Unlevered Free Cash Flow Stub Adjusted | E45: =E40*D9 -> 803.89522 | F45: =F40 -> 1359.7744 | G45: =G40 -> 1463.9866 | H45: =H40 -> 1750.586 | I45: =I40 -> 1791.1177
C46: PV Factor | E46: =1/(1+$H$5)^((E43-$D$43)/365) -> 0.97994914 | F46: =1/(1+$H$5)^((F43-$D$43)/365) -> 0.92307608 | G46: =1/(1+$H$5)^((G43-$D$43)/365) -> 0.85280809 | H46: =1/(1+$H$5)^((H43-$D$43)/365) -> 0.78788916 | I46: =1/(1+$H$5)^((I43-$D$43)/365) -> 0.72799095
C47: PV of Unlevered Free Cash Flow | E47: =E45*E46 -> 787.77643 | F47: =F45*F46 -> 1255.1752 | G47: =G45*G46 -> 1248.4996 | H47: =H45*H46 -> 1379.2677 | I47: =I45*I46 -> 1303.9174
B50: x | C50: Terminal Value - Gordon Growth | F50: Net Debt
C51: Long-term growth rate | D51: 0.035 | F51: Gross debt and equivalents
C52: 2030 FCF x (1+g) | D52: =I40*(1+D51) -> 1853.8068 | F52: Debt | I52: =Financials!F67 -> 1884
C53: Terminal value | D53: =D52/(H5-D51) -> 39210.12 | F53: Convertible debt | I53: 0
C54: PV of terminal value | D54: =D53/(1+H5)^((I43-D43)/365) -> 28544.612 | F54: Preferred stock | I54: 0
C55: PV of stage 1 cash flows | D55: =SUM(E47:I47) -> 5974.6364 | F55: Operating lease liabilities | I55: 0
C56: Total Enterprise Value | D56: =D54+D55 -> 34519.249 | F56: Noncontrolling interests | I56: 0
F57: Nonoperating assets
C58: Terminal value as % of TEV | D58: =D54/D56 -> 0.8269187 | F58: Cash and marketable securities | I58: =-Financials!F55 -> -2248
C59: Stage 1 cash flows as % of TEV | D59: =D55/D56 -> 0.1730813
C60: Implied TV exit EBITDA multiple | D60: =D53/Financials!K38 -> 11.183666 | F60: Net Debt | I60: =SUM(I58,I52:I56) -> -364
C62: Terminal Value - Exit Multiple | F62: Shares Outstanding
C63: Terminal year EBITDA | D63: =Financials!K38 -> 3506.0166 | F63: Basic shares | I63: =Financials!D7 -> 250.25371
C64: EBITDA multiple | D64: =LBO!D16 -> 31.5 | F64: Restricted stock/RSUs | I64: 7.832
C65: Terminal value | D65: =D63*D64 -> 110439.52 | F65: SARs/Options | I65: 0.003
C66: PV of terminal value | D66: =D65/(1+H5)^((I43-D43)/365) -> 80398.974 | F66: Total proceeds | I66: =I65*56.22 -> 0.16866
C67: PV of stage 1 cash flows | D67: =SUM(E47:I47) -> 5974.6364 | F67: Shares repurchased | I67: =I66/LBO!D9 -> 0.00100202
C68: Total Enterprise Value | D68: =D66+D67 -> 86373.611 | F68: Net dilutive impact of SARs/Options | I68: =I65-I67 -> 0.00199798
F69: Convertible debt | I69: 0
C70: Terminal value as % of TEV | D70: =D66/D68 -> 0.93082799 | F70: Convertible preferred stock | I70: 0
C71: Stage 1 cash flows as % of TEV | D71: =D67/D68 -> 0.069172011
C72: Implied terminal growth rate | D72: =(H5-I45/D65)/(1+I45/D65) -> 0.065006419 | F72: Net Diluted Shares Outstanding | I72: =SUM(I63,I64,I68) -> 258.08771
B75: x | C75: VALUATION
D77: LBO Offer | E77: Perpetuity | F77: EBITDA
C78: Enterprise value | E78: =D56 -> 34519.249 | F78: =D68 -> 86373.611
C79: Net debt | E79: =$I$60 -> -364 | F79: =$I$60 -> -364
C80: Equity value | D80: =LBO!D31 -> 54198.419 | E80: =SUM(E78:E79) -> 34155.249 | F80: =SUM(F78:F79) -> 86009.611
C81: Shares outstanding | D81: =$I$72 -> 258.08771 | E81: =$I$72 -> 258.08771 | F81: =$I$72 -> 258.08771
C82: Equity value per share | D82: =D80/D81 -> 210 | E82: =E80/E81 -> 132.33969 | F82: =F80/F81 -> 333.25729
C83: Premium/Discount to LBO Offer | E83: =E82/D82-1 -> -0.36981098 | F83: =F82/D82-1 -> 0.58693947
